qts/QtCore.py
qts/QtGui.py
qts/QtWidgets.py
qts/__init__.py
qts/__main__.py
qts/_cli.py
qts/_core.py
qts/_errors.py
qts/_version.py
qts/py.typed
qts/util.py
qts/_tests/__init__.py
qts/_tests/conftest.py
qts/_tests/test_cli.py
qts/_tests/test_core.py
qts/_tests/test_overall.py
qts/_tests/test_util.py
qts/_tests/qt/__init__.py
qts/_tests/qt/test_core.py
qts/_tests/qt/test_gui.py
qts/_tests/qt/test_widgets.py
qts-0.3.dist-info/LICENSE
qts-0.3.dist-info/METADATA
qts-0.3.dist-info/WHEEL
qts-0.3.dist-info/entry_points.txt
qts-0.3.dist-info/top_level.txt
qts-0.3.dist-info/RECORD
