Metadata-Version: 2.1
Name: qts
Version: 0.3
Summary: a thin compatibility layer for Python code to use Qt through various wrappers
Home-page: https://github.com/altendky/qts
Author: Kyle Altendorf
Author-email: sda@fstab.net
License: MIT
Project-URL: Documentation, https://qts.readthedocs.io/
Project-URL: Issues, https://github.com/python-qt-tools/qts/issues
Project-URL: Repository, https://github.com/python-qt-tools/qts
Project-URL: Tests, https://github.com/python-qt-tools/qts/actions?query=branch%3Amain
Project-URL: Coverage, https://codecov.io/gh/python-qt-tools/qts
Project-URL: Distribution, https://pypi.org/project/qts
Keywords: GUI,Qt,PyQt5,PySide2,PyQt6,PySide6
Classifier: License :: OSI Approved :: MIT License
Classifier: Operating System :: POSIX :: Linux
Classifier: Operating System :: MacOS :: MacOS X
Classifier: Operating System :: Microsoft :: Windows
Classifier: Programming Language :: Python :: 3 :: Only
Classifier: Programming Language :: Python :: 3.6
Classifier: Programming Language :: Python :: 3.7
Classifier: Programming Language :: Python :: 3.8
Classifier: Programming Language :: Python :: 3.9
Classifier: Programming Language :: Python :: Implementation :: CPython
Classifier: Development Status :: 3 - Alpha
Classifier: Intended Audience :: Developers
Classifier: Topic :: Software Development :: User Interfaces
Requires-Python: >=3.6
License-File: LICENSE
Requires-Dist: attrs (>=20.1.0)
Requires-Dist: typing-extensions (>=3.10)
Provides-Extra: cli
Requires-Dist: click (~=8.0) ; extra == 'cli'
Provides-Extra: p_checks
Requires-Dist: check-manifest (~=0.46.0) ; extra == 'p_checks'
Requires-Dist: flake8 (~=3.8) ; extra == 'p_checks'
Requires-Dist: mypy (==0.901) ; extra == 'p_checks'
Requires-Dist: pytest (~=6.2) ; extra == 'p_checks'
Requires-Dist: towncrier (~=21.3) ; extra == 'p_checks'
Requires-Dist: black (==22.10.0) ; (python_version >= "3.7") and extra == 'p_checks'
Provides-Extra: p_docs
Requires-Dist: importlib-metadata (~=4.5) ; extra == 'p_docs'
Requires-Dist: pyside2 (~=5.15) ; extra == 'p_docs'
Requires-Dist: sphinx (~=4.0) ; extra == 'p_docs'
Requires-Dist: sphinx-autodoc-typehints (~=1.11) ; extra == 'p_docs'
Requires-Dist: sphinx-click (~=3.0) ; extra == 'p_docs'
Requires-Dist: sphinx-inline-tabs (~=2020.10.19b4) ; extra == 'p_docs'
Requires-Dist: sphinx-qt-documentation (~=0.3.0) ; extra == 'p_docs'
Requires-Dist: sphinx-rtd-theme (~=0.5.0) ; extra == 'p_docs'
Requires-Dist: towncrier (~=21.3) ; extra == 'p_docs'
Provides-Extra: p_tests
Requires-Dist: click (~=8.0) ; extra == 'p_tests'
Requires-Dist: coverage (~=5.5) ; extra == 'p_tests'
Requires-Dist: pytest (~=6.2) ; extra == 'p_tests'
Requires-Dist: pytest-cov (~=2.12) ; extra == 'p_tests'
Requires-Dist: pytest-xvfb (~=2.0) ; (sys_platform == "linux") and extra == 'p_tests'
Provides-Extra: pyqt5
Requires-Dist: pyqt5 (~=5.15) ; extra == 'pyqt5'
Provides-Extra: pyqt6
Requires-Dist: pyqt6 (~=6.0) ; extra == 'pyqt6'
Provides-Extra: pyside2
Requires-Dist: pyside2 (~=5.15) ; extra == 'pyside2'
Provides-Extra: pyside6
Requires-Dist: pyside6 (~=6.0) ; extra == 'pyside6'
Provides-Extra: s_pytest
Requires-Dist: pytest (~=6.2) ; extra == 's_pytest'
Provides-Extra: s_towncrier
Requires-Dist: towncrier (~=21.3) ; extra == 's_towncrier'
